_pylibmc.cpython-38-darwin.so
pylibmc-1.6.3.dist-info/RECORD
pylibmc-1.6.3.dist-info/LICENSE
pylibmc-1.6.3.dist-info/WHEEL
pylibmc-1.6.3.dist-info/top_level.txt
pylibmc-1.6.3.dist-info/METADATA
pylibmc/autoconf.py
pylibmc/pools.py
pylibmc/client.py
pylibmc/__init__.py
pylibmc/test.py
pylibmc/consts.py
pylibmc/__main__.py
pylibmc/.dylibs/libhashkit.2.0.0.dylib
pylibmc/.dylibs/libmemcached.11.0.0.dylib
