Metadata-Version: 1.1
Name: pylibmc
Version: 1.6.3
Summary: Quick and small memcached client for Python
Home-page: https://sendapatch.se/projects/pylibmc/
Author: Ludvig Ericson
Author-email: ludvig@lericson.se
License: 3-clause BSD <https://opensource.org/licenses/bsd-license.php>
Platform: UNKNOWN
Classifier: Programming Language :: Python
Classifier: Programming Language :: Python :: 3
Classifier: Programming Language :: Python :: 3.6
Classifier: Programming Language :: Python :: 3.7
Classifier: Programming Language :: Python :: 3.8
Classifier: Programming Language :: Python :: 3.9
Classifier: Programming Language :: Python :: 3.10
Classifier: Programming Language :: Python :: 3 :: Only
